fsorter/__init__.py
fsorter/fsorter.py
fsorter-2.4.1.dist-info/METADATA
fsorter-2.4.1.dist-info/WHEEL
fsorter-2.4.1.dist-info/top_level.txt
fsorter-2.4.1.dist-info/RECORD
