Metadata-Version: 2.1
Name: fsorter
Version: 2.4.1
Summary: File sorting program according to the numbers in the file name.
Home-page: https://github.com/kadirrbrtt/fsorter
Author: Kadir Barut
Author-email: kadirrbrtt@gmail.com
License: MIT
Platform: UNKNOWN
Classifier: License :: OSI Approved :: MIT License
Classifier: Programming Language :: Python :: 3
Classifier: Programming Language :: Python :: 3.8
